[{"group":"Insects","obs_count":8480,"login":"elaphrornis","icon_url":"https://static.inaturalist.org/attachments/users/icons/279977/medium.jpg?1475529744","taxon_id_string":"47158\u0026place_id=7077","rank":1},{"group":"Birds","obs_count":4624,"login":"sethmiller","icon_url":"https://static.inaturalist.org/attachments/users/icons/1463753/medium.jpg?1549545397","taxon_id_string":"3\u0026place_id=7077","rank":2},{"group":"Plants","obs_count":2868,"login":"nuwan","icon_url":"https://static.inaturalist.org/attachments/users/icons/8828/medium.jpg?1530698360","taxon_id_string":"211194,311249\u0026place_id=7077","rank":3},{"group":"Reptiles and Amphibians","obs_count":2826,"login":"tom-kirschey-nabu","icon_url":"https://static.inaturalist.org/attachments/users/icons/155951/medium.jpeg?1543747758","taxon_id_string":"26036,20978\u0026place_id=7077","rank":4},{"group":"Mammals","obs_count":1303,"login":"jwidness","icon_url":null,"taxon_id_string":"40151\u0026place_id=7077","rank":5},{"group":"Arachnids","obs_count":795,"login":"elaphrornis","icon_url":"https://static.inaturalist.org/attachments/users/icons/279977/medium.jpg?1475529744","taxon_id_string":"47119\u0026place_id=7077","rank":6},{"group":"Fishes","obs_count":420,"login":"maractwin","icon_url":"https://static.inaturalist.org/attachments/users/icons/10787/medium.jpg?1479735613","taxon_id_string":"47178,47273,49231,60450,49099,85497\u0026place_id=7077","rank":7},{"group":"Other Species","obs_count":401,"login":"elaphrornis","icon_url":"https://static.inaturalist.org/attachments/users/icons/279977/medium.jpg?1475529744","taxon_id_string":"85493,47549,47534,144128,48222,47491,47686,130868,52319\u0026place_id=7077","rank":8},{"group":"Molluscs","obs_count":356,"login":"amila_sumanapala","icon_url":"https://static.inaturalist.org/attachments/users/icons/56488/medium.jpeg?1553491861","taxon_id_string":"47115\u0026place_id=7077","rank":9},{"group":"Fungi","obs_count":334,"login":"juhakinnunen","icon_url":"https://static.inaturalist.org/attachments/users/icons/614374/medium.gif?1542975190","taxon_id_string":"47170\u0026place_id=7077","rank":10}]