[{"group":"Birds","obs_count":246,"login":"jakob","icon_url":"https://static.inaturalist.org/attachments/users/icons/5643/medium.png?1475530151","taxon_id_string":"3\u0026place_id=9173","rank":1},{"group":"Plants","obs_count":147,"login":"jakob","icon_url":"https://static.inaturalist.org/attachments/users/icons/5643/medium.png?1475530151","taxon_id_string":"211194,311249\u0026place_id=9173","rank":2},{"group":"Insects","obs_count":143,"login":"jakob","icon_url":"https://static.inaturalist.org/attachments/users/icons/5643/medium.png?1475530151","taxon_id_string":"47158\u0026place_id=9173","rank":3},{"group":"Fungi","obs_count":99,"login":"jakob","icon_url":"https://static.inaturalist.org/attachments/users/icons/5643/medium.png?1475530151","taxon_id_string":"47170\u0026place_id=9173","rank":4},{"group":"Reptiles and Amphibians","obs_count":91,"login":"jakob","icon_url":"https://static.inaturalist.org/attachments/users/icons/5643/medium.png?1475530151","taxon_id_string":"26036,20978\u0026place_id=9173","rank":5},{"group":"Fishes","obs_count":52,"login":"jakob","icon_url":"https://static.inaturalist.org/attachments/users/icons/5643/medium.png?1475530151","taxon_id_string":"47178,47273,49231,60450,49099,85497\u0026place_id=9173","rank":6},{"group":"Other Species","obs_count":52,"login":"jakob","icon_url":"https://static.inaturalist.org/attachments/users/icons/5643/medium.png?1475530151","taxon_id_string":"85493,47549,47534,144128,48222,47491,47686,130868,52319\u0026place_id=9173","rank":7},{"group":"Molluscs","obs_count":42,"login":"jakob","icon_url":"https://static.inaturalist.org/attachments/users/icons/5643/medium.png?1475530151","taxon_id_string":"47115\u0026place_id=9173","rank":8},{"group":"Arachnids","obs_count":33,"login":"jakob","icon_url":"https://static.inaturalist.org/attachments/users/icons/5643/medium.png?1475530151","taxon_id_string":"47119\u0026place_id=9173","rank":9},{"group":"Mammals","obs_count":21,"login":"jakob","icon_url":"https://static.inaturalist.org/attachments/users/icons/5643/medium.png?1475530151","taxon_id_string":"40151\u0026place_id=9173","rank":10}]