[{"rank":43,"place_id":7042,"place_name":"Kenya","obs_count":28374,"observers":[{"user_id":983231,"observation_count":2073,"species_count":753,"user":{"id":983231,"login":"designedforx","spam":false,"suspended":false,"created_at":"2018-05-24T08:00:58+00:00","login_autocomplete":"designedforx","login_exact":"designedforx","name":"Ewout Knoester","name_autocomplete":"Ewout Knoester","orcid":null,"icon":null,"observations_count":2183,"identifications_count":586,"journal_posts_count":0,"activity_count":2769,"universal_search_rank":2183,"roles":[],"site_id":1,"icon_url":null}},{"user_id":97044,"observation_count":1626,"species_count":302,"user":{"id":97044,"login":"waswala","spam":false,"suspended":false,"created_at":"2015-05-08T05:58:29+00:00","login_autocomplete":"waswala","login_exact":"waswala","name":"Marvis Olewe","name_autocomplete":"Marvis Olewe","orcid":null,"icon":"https://static.inaturalist.org/attachments/users/icons/97044/thumb.jpeg?1501692476","observations_count":2259,"identifications_count":1252,"journal_posts_count":0,"activity_count":3511,"universal_search_rank":2259,"roles":[],"site_id":1,"icon_url":"https://static.inaturalist.org/attachments/users/icons/97044/medium.jpeg?1501692476"}},{"user_id":292489,"observation_count":1119,"species_count":155,"user":{"id":292489,"login":"elliotgreiner","spam":false,"suspended":false,"created_at":"2016-08-07T18:02:03+00:00","login_autocomplete":"elliotgreiner","login_exact":"elliotgreiner","name":"Elliot Greiner","name_autocomplete":"Elliot Greiner","orcid":null,"icon":"https://static.inaturalist.org/attachments/users/icons/292489/thumb.jpg?1503547201","observations_count":9784,"identifications_count":5311,"journal_posts_count":0,"activity_count":15095,"universal_search_rank":9784,"roles":[],"site_id":1,"icon_url":"https://static.inaturalist.org/attachments/users/icons/292489/medium.jpg?1503547201"}},{"user_id":375489,"observation_count":1064,"species_count":442,"user":{"id":375489,"login":"mjplagens","spam":false,"suspended":false,"created_at":"2016-11-27T20:27:26+00:00","login_autocomplete":"mjplagens","login_exact":"mjplagens","name":"Mike Plagens","name_autocomplete":"Mike Plagens","orcid":null,"icon":"https://static.inaturalist.org/attachments/users/icons/375489/thumb.jpg?1542047976","observations_count":5097,"identifications_count":15801,"journal_posts_count":2,"activity_count":20900,"universal_search_rank":5097,"roles":["curator"],"site_id":1,"icon_url":"https://static.inaturalist.org/attachments/users/icons/375489/medium.jpg?1542047976"}},{"user_id":94627,"observation_count":1023,"species_count":203,"user":{"id":94627,"login":"amarzee","spam":false,"suspended":false,"created_at":"2015-04-30T05:59:51+00:00","login_autocomplete":"amarzee","login_exact":"amarzee","name":"Amaël Borzée","name_autocomplete":"Amaël Borzée","orcid":null,"icon":"https://static.inaturalist.org/attachments/users/icons/94627/thumb.jpg?1475549667","observations_count":12571,"identifications_count":5071,"journal_posts_count":0,"activity_count":17642,"universal_search_rank":12571,"roles":["curator"],"site_id":1,"icon_url":"https://static.inaturalist.org/attachments/users/icons/94627/medium.jpg?1475549667"}}],"identifiers":[{"user_id":520,"count":5361,"user":{"id":520,"login":"johnnybirder","spam":false,"suspended":false,"created_at":"2011-01-19T16:58:30+00:00","login_autocomplete":"johnnybirder","login_exact":"johnnybirder","name":"Johnny Wilson","name_autocomplete":"Johnny Wilson","orcid":null,"icon":"https://static.inaturalist.org/attachments/users/icons/520/thumb.jpg?1475527599","observations_count":7377,"identifications_count":55946,"journal_posts_count":0,"activity_count":63323,"universal_search_rank":7377,"roles":["curator"],"site_id":1,"icon_url":"https://static.inaturalist.org/attachments/users/icons/520/medium.jpg?1475527599"}},{"user_id":5643,"count":5120,"user":{"id":5643,"login":"jakob","spam":false,"suspended":false,"created_at":"2012-04-02T10:00:13+00:00","login_autocomplete":"jakob","login_exact":"jakob","name":"Jakob Fahr","name_autocomplete":"Jakob Fahr","orcid":null,"icon":"https://static.inaturalist.org/attachments/users/icons/5643/thumb.png?1475530151","observations_count":14154,"identifications_count":127960,"journal_posts_count":2,"activity_count":142116,"universal_search_rank":14154,"roles":["curator"],"site_id":1,"icon_url":"https://static.inaturalist.org/attachments/users/icons/5643/medium.png?1475530151"}},{"user_id":29729,"count":3409,"user":{"id":29729,"login":"ldacosta","spam":false,"suspended":false,"created_at":"2014-02-02T19:12:57+00:00","login_autocomplete":"ldacosta","login_exact":"ldacosta","name":"Luis da Costa","name_autocomplete":"Luis da Costa","orcid":null,"icon":"https://static.inaturalist.org/attachments/users/icons/29729/thumb.jpeg?1475543064","observations_count":4640,"identifications_count":162702,"journal_posts_count":0,"activity_count":167342,"universal_search_rank":4640,"roles":["curator"],"site_id":1,"icon_url":"https://static.inaturalist.org/attachments/users/icons/29729/medium.jpeg?1475543064"}},{"user_id":560165,"count":2590,"user":{"id":560165,"login":"calebcam","spam":false,"suspended":false,"created_at":"2017-08-03T22:47:36+00:00","login_autocomplete":"calebcam","login_exact":"calebcam","name":"calebcam","name_autocomplete":"calebcam","orcid":null,"icon":"https://static.inaturalist.org/attachments/users/icons/560165/thumb.jpg?1559091578","observations_count":3872,"identifications_count":88938,"journal_posts_count":4,"activity_count":92814,"universal_search_rank":3872,"roles":[],"site_id":1,"icon_url":"https://static.inaturalist.org/attachments/users/icons/560165/medium.jpg?1559091578"}},{"user_id":854537,"count":2170,"user":{"id":854537,"login":"maxallen","spam":false,"suspended":false,"created_at":"2018-04-16T22:12:08+00:00","login_autocomplete":"maxallen","login_exact":"maxallen","name":"","name_autocomplete":"","orcid":null,"icon":"https://static.inaturalist.org/attachments/users/icons/854537/thumb.jpg?1529523533","observations_count":384,"identifications_count":246848,"journal_posts_count":3,"activity_count":247235,"universal_search_rank":384,"roles":["curator"],"site_id":1,"icon_url":"https://static.inaturalist.org/attachments/users/icons/854537/medium.jpg?1529523533"}}]},{"rank":44,"place_id":7599,"place_name":"Sweden","obs_count":27276,"observers":[{"user_id":77260,"observation_count":2427,"species_count":896,"user":{"id":77260,"login":"evahedstrom","spam":false,"suspended":false,"created_at":"2015-02-17T20:25:39+00:00","login_autocomplete":"evahedstrom","login_exact":"evahedstrom","name":"Eva Hedström","name_autocomplete":"Eva Hedström","orcid":null,"icon":"https://static.inaturalist.org/attachments/users/icons/77260/thumb.jpg?1475553042","observations_count":6897,"identifications_count":1828,"journal_posts_count":0,"activity_count":8725,"universal_search_rank":6897,"roles":["curator"],"site_id":1,"icon_url":"https://static.inaturalist.org/attachments/users/icons/77260/medium.jpg?1475553042"}},{"user_id":582896,"observation_count":2023,"species_count":538,"user":{"id":582896,"login":"smithb","spam":false,"suspended":false,"created_at":"2017-08-16T09:49:11+00:00","login_autocomplete":"smithb","login_exact":"smithb","name":"Bryan Smith","name_autocomplete":"Bryan Smith","orcid":null,"icon":"https://static.inaturalist.org/attachments/users/icons/582896/thumb.jpg?1502888458","observations_count":2182,"identifications_count":73,"journal_posts_count":0,"activity_count":2255,"universal_search_rank":2182,"roles":[],"site_id":1,"icon_url":"https://static.inaturalist.org/attachments/users/icons/582896/medium.jpg?1502888458"}},{"user_id":20274,"observation_count":1067,"species_count":225,"user":{"id":20274,"login":"keithwlarson","spam":false,"suspended":false,"created_at":"2013-08-12T12:28:10+00:00","login_autocomplete":"keithwlarson","login_exact":"keithwlarson","name":"Keith W. Larson","name_autocomplete":"Keith W. Larson","orcid":null,"icon":"https://static.inaturalist.org/attachments/users/icons/20274/thumb.jpg?1475538317","observations_count":1185,"identifications_count":411,"journal_posts_count":0,"activity_count":1596,"universal_search_rank":1185,"roles":[],"site_id":1,"icon_url":"https://static.inaturalist.org/attachments/users/icons/20274/medium.jpg?1475538317"}},{"user_id":1354686,"observation_count":1040,"species_count":630,"user":{"id":1354686,"login":"wildchroma","spam":false,"suspended":false,"created_at":"2018-11-16T19:58:34+00:00","login_autocomplete":"wildchroma","login_exact":"wildchroma","name":"","name_autocomplete":"","orcid":null,"icon":"https://static.inaturalist.org/attachments/users/icons/1354686/thumb.jpeg?1543275984","observations_count":4545,"identifications_count":2584,"journal_posts_count":0,"activity_count":7129,"universal_search_rank":4545,"roles":[],"site_id":1,"icon_url":"https://static.inaturalist.org/attachments/users/icons/1354686/medium.jpeg?1543275984"}},{"user_id":404218,"observation_count":986,"species_count":466,"user":{"id":404218,"login":"veronika_johansson","spam":false,"suspended":false,"created_at":"2017-02-10T13:42:27+00:00","login_autocomplete":"veronika_johansson","login_exact":"veronika_johansson","name":"Veronika Johansson","name_autocomplete":"Veronika Johansson","orcid":null,"icon":"https://static.inaturalist.org/attachments/users/icons/404218/thumb.jpg?1528896694","observations_count":1057,"identifications_count":9888,"journal_posts_count":0,"activity_count":10945,"universal_search_rank":1057,"roles":[],"site_id":1,"icon_url":"https://static.inaturalist.org/attachments/users/icons/404218/medium.jpg?1528896694"}}],"identifiers":[{"user_id":534826,"count":1884,"user":{"id":534826,"login":"jmgrinde","spam":false,"suspended":false,"created_at":"2017-07-16T14:19:15+00:00","login_autocomplete":"jmgrinde","login_exact":"jmgrinde","name":"","name_autocomplete":"","orcid":null,"icon":null,"observations_count":2296,"identifications_count":11956,"journal_posts_count":0,"activity_count":14252,"universal_search_rank":2296,"roles":[],"site_id":1,"icon_url":null}},{"user_id":404218,"count":1764,"user":{"id":404218,"login":"veronika_johansson","spam":false,"suspended":false,"created_at":"2017-02-10T13:42:27+00:00","login_autocomplete":"veronika_johansson","login_exact":"veronika_johansson","name":"Veronika Johansson","name_autocomplete":"Veronika Johansson","orcid":null,"icon":"https://static.inaturalist.org/attachments/users/icons/404218/thumb.jpg?1528896694","observations_count":1057,"identifications_count":9888,"journal_posts_count":0,"activity_count":10945,"universal_search_rank":1057,"roles":[],"site_id":1,"icon_url":"https://static.inaturalist.org/attachments/users/icons/404218/medium.jpg?1528896694"}},{"user_id":29729,"count":1421,"user":{"id":29729,"login":"ldacosta","spam":false,"suspended":false,"created_at":"2014-02-02T19:12:57+00:00","login_autocomplete":"ldacosta","login_exact":"ldacosta","name":"Luis da Costa","name_autocomplete":"Luis da Costa","orcid":null,"icon":"https://static.inaturalist.org/attachments/users/icons/29729/thumb.jpeg?1475543064","observations_count":4640,"identifications_count":162702,"journal_posts_count":0,"activity_count":167342,"universal_search_rank":4640,"roles":["curator"],"site_id":1,"icon_url":"https://static.inaturalist.org/attachments/users/icons/29729/medium.jpeg?1475543064"}},{"user_id":614374,"count":1355,"user":{"id":614374,"login":"juhakinnunen","spam":false,"suspended":false,"created_at":"2017-09-03T19:28:24+00:00","login_autocomplete":"juhakinnunen","login_exact":"juhakinnunen","name":"Juha Kinnunen","name_autocomplete":"Juha Kinnunen","orcid":null,"icon":"https://static.inaturalist.org/attachments/users/icons/614374/thumb.gif?1542975190","observations_count":5278,"identifications_count":50611,"journal_posts_count":0,"activity_count":55889,"universal_search_rank":5278,"roles":["curator"],"site_id":1,"icon_url":"https://static.inaturalist.org/attachments/users/icons/614374/medium.gif?1542975190"}},{"user_id":395425,"count":1305,"user":{"id":395425,"login":"nannie","spam":false,"suspended":false,"created_at":"2017-01-26T09:21:47+00:00","login_autocomplete":"nannie","login_exact":"nannie","name":"Nannie","name_autocomplete":"Nannie","orcid":null,"icon":"https://static.inaturalist.org/attachments/users/icons/395425/thumb.jpg?1502456253","observations_count":682,"identifications_count":5778,"journal_posts_count":0,"activity_count":6460,"universal_search_rank":682,"roles":[],"site_id":1,"icon_url":"https://static.inaturalist.org/attachments/users/icons/395425/medium.jpg?1502456253"}}]},{"rank":45,"place_id":6873,"place_name":"Philippines","obs_count":25388,"observers":[{"user_id":10787,"observation_count":1829,"species_count":716,"user":{"id":10787,"login":"maractwin","spam":false,"suspended":false,"created_at":"2012-10-31T16:08:52+00:00","login_autocomplete":"maractwin","login_exact":"maractwin","name":"Mark Rosenstein","name_autocomplete":"Mark Rosenstein","orcid":null,"icon":"https://static.inaturalist.org/attachments/users/icons/10787/thumb.jpg?1479735613","observations_count":35270,"identifications_count":234622,"journal_posts_count":24,"activity_count":269916,"universal_search_rank":35270,"roles":["curator"],"site_id":1,"icon_url":"https://static.inaturalist.org/attachments/users/icons/10787/medium.jpg?1479735613"}},{"user_id":384273,"observation_count":1546,"species_count":299,"user":{"id":384273,"login":"rhabdornis","spam":false,"suspended":false,"created_at":"2016-12-28T13:35:45+00:00","login_autocomplete":"rhabdornis","login_exact":"rhabdornis","name":null,"name_autocomplete":null,"orcid":null,"icon":null,"observations_count":1814,"identifications_count":250,"journal_posts_count":0,"activity_count":2064,"universal_search_rank":1814,"roles":[],"site_id":1,"icon_url":null}},{"user_id":726708,"observation_count":1269,"species_count":238,"user":{"id":726708,"login":"curiousann","spam":false,"suspended":false,"created_at":"2017-12-05T11:19:26+00:00","login_autocomplete":"curiousann","login_exact":"curiousann","name":"AnnLazaro","name_autocomplete":"AnnLazaro","orcid":null,"icon":"https://static.inaturalist.org/attachments/users/icons/726708/thumb.jpg?1556201975","observations_count":1370,"identifications_count":329,"journal_posts_count":0,"activity_count":1699,"universal_search_rank":1370,"roles":[],"site_id":1,"icon_url":"https://static.inaturalist.org/attachments/users/icons/726708/medium.jpg?1556201975"}},{"user_id":144177,"observation_count":991,"species_count":393,"user":{"id":144177,"login":"greg3ph","spam":false,"suspended":false,"created_at":"2015-10-16T10:47:01+00:00","login_autocomplete":"greg3ph","login_exact":"greg3ph","name":"Greg III Espera","name_autocomplete":"Greg III Espera","orcid":null,"icon":"https://static.inaturalist.org/attachments/users/icons/144177/thumb.png?1528081278","observations_count":1127,"identifications_count":3377,"journal_posts_count":0,"activity_count":4504,"universal_search_rank":1127,"roles":[],"site_id":1,"icon_url":"https://static.inaturalist.org/attachments/users/icons/144177/medium.png?1528081278"}},{"user_id":104203,"observation_count":975,"species_count":395,"user":{"id":104203,"login":"liselle","spam":false,"suspended":false,"created_at":"2015-05-23T14:20:22+00:00","login_autocomplete":"liselle","login_exact":"liselle","name":"Liselle Santos","name_autocomplete":"Liselle Santos","orcid":null,"icon":"https://static.inaturalist.org/attachments/users/icons/104203/thumb.jpg?1521623906","observations_count":1023,"identifications_count":1702,"journal_posts_count":3,"activity_count":2728,"universal_search_rank":1023,"roles":[],"site_id":1,"icon_url":"https://static.inaturalist.org/attachments/users/icons/104203/medium.jpg?1521623906"}}],"identifiers":[{"user_id":10787,"count":2979,"user":{"id":10787,"login":"maractwin","spam":false,"suspended":false,"created_at":"2012-10-31T16:08:52+00:00","login_autocomplete":"maractwin","login_exact":"maractwin","name":"Mark Rosenstein","name_autocomplete":"Mark Rosenstein","orcid":null,"icon":"https://static.inaturalist.org/attachments/users/icons/10787/thumb.jpg?1479735613","observations_count":35270,"identifications_count":234622,"journal_posts_count":24,"activity_count":269916,"universal_search_rank":35270,"roles":["curator"],"site_id":1,"icon_url":"https://static.inaturalist.org/attachments/users/icons/10787/medium.jpg?1479735613"}},{"user_id":517807,"count":1163,"user":{"id":517807,"login":"kemper","spam":false,"suspended":false,"created_at":"2017-06-26T02:24:03+00:00","login_autocomplete":"kemper","login_exact":"kemper","name":"Yann Kemper","name_autocomplete":"Yann Kemper","orcid":null,"icon":"https://static.inaturalist.org/attachments/users/icons/517807/thumb.jpeg?1542590516","observations_count":5986,"identifications_count":80244,"journal_posts_count":1,"activity_count":86231,"universal_search_rank":5986,"roles":[],"site_id":1,"icon_url":"https://static.inaturalist.org/attachments/users/icons/517807/medium.jpeg?1542590516"}},{"user_id":405817,"count":765,"user":{"id":405817,"login":"hsini_lin","spam":false,"suspended":false,"created_at":"2017-02-13T07:34:12+00:00","login_autocomplete":"hsini_lin","login_exact":"hsini_lin","name":"Hsini Lin","name_autocomplete":"Hsini Lin","orcid":null,"icon":null,"observations_count":6,"identifications_count":4728,"journal_posts_count":0,"activity_count":4734,"universal_search_rank":6,"roles":["curator"],"site_id":1,"icon_url":null}},{"user_id":630365,"count":745,"user":{"id":630365,"login":"joe_fish","spam":false,"suspended":false,"created_at":"2017-09-15T16:19:47+00:00","login_autocomplete":"joe_fish","login_exact":"joe_fish","name":"","name_autocomplete":"","orcid":null,"icon":"https://static.inaturalist.org/attachments/users/icons/630365/thumb.jpg?1530807567","observations_count":1,"identifications_count":8738,"journal_posts_count":0,"activity_count":8739,"universal_search_rank":1,"roles":[],"site_id":1,"icon_url":"https://static.inaturalist.org/attachments/users/icons/630365/medium.jpg?1530807567"}},{"user_id":217955,"count":735,"user":{"id":217955,"login":"phelsumas4life","spam":false,"suspended":false,"created_at":"2016-04-16T04:12:27+00:00","login_autocomplete":"phelsumas4life","login_exact":"phelsumas4life","name":"Sean Ono","name_autocomplete":"Sean Ono","orcid":null,"icon":"https://static.inaturalist.org/attachments/users/icons/217955/thumb.jpg?1527723689","observations_count":330,"identifications_count":48164,"journal_posts_count":0,"activity_count":48494,"universal_search_rank":330,"roles":[],"site_id":1,"icon_url":"https://static.inaturalist.org/attachments/users/icons/217955/medium.jpg?1527723689"}}]},{"rank":46,"place_id":7016,"place_name":"Norway","obs_count":24542,"observers":[{"user_id":23197,"observation_count":4554,"species_count":67,"user":{"id":23197,"login":"tinekk","spam":false,"suspended":false,"created_at":"2013-09-30T19:30:03+00:00","login_autocomplete":"tinekk","login_exact":"tinekk","name":"Tine Kinn Kvamme","name_autocomplete":"Tine Kinn Kvamme","orcid":null,"icon":"https://static.inaturalist.org/attachments/users/icons/23197/thumb.jpg?1504104720","observations_count":5127,"identifications_count":689,"journal_posts_count":0,"activity_count":5816,"universal_search_rank":5127,"roles":[],"site_id":1,"icon_url":"https://static.inaturalist.org/attachments/users/icons/23197/medium.jpg?1504104720"}},{"user_id":534826,"observation_count":2171,"species_count":722,"user":{"id":534826,"login":"jmgrinde","spam":false,"suspended":false,"created_at":"2017-07-16T14:19:15+00:00","login_autocomplete":"jmgrinde","login_exact":"jmgrinde","name":"","name_autocomplete":"","orcid":null,"icon":null,"observations_count":2296,"identifications_count":11956,"journal_posts_count":0,"activity_count":14252,"universal_search_rank":2296,"roles":[],"site_id":1,"icon_url":null}},{"user_id":26121,"observation_count":2062,"species_count":507,"user":{"id":26121,"login":"wouterkoch","spam":false,"suspended":false,"created_at":"2013-11-19T13:06:38+00:00","login_autocomplete":"wouterkoch","login_exact":"wouterkoch","name":"Wouter Koch","name_autocomplete":"Wouter Koch","orcid":null,"icon":"https://static.inaturalist.org/attachments/users/icons/26121/thumb.jpg?1475540931","observations_count":4645,"identifications_count":6899,"journal_posts_count":0,"activity_count":11544,"universal_search_rank":4645,"roles":[],"site_id":1,"icon_url":"https://static.inaturalist.org/attachments/users/icons/26121/medium.jpg?1475540931"}},{"user_id":160529,"observation_count":889,"species_count":301,"user":{"id":160529,"login":"ttyl","spam":false,"suspended":false,"created_at":"2015-12-12T12:36:17+00:00","login_autocomplete":"ttyl","login_exact":"ttyl","name":"ttyl","name_autocomplete":"ttyl","orcid":null,"icon":null,"observations_count":907,"identifications_count":0,"journal_posts_count":0,"activity_count":907,"universal_search_rank":907,"roles":[],"site_id":1,"icon_url":null}},{"user_id":730989,"observation_count":742,"species_count":36,"user":{"id":730989,"login":"jornari","spam":false,"suspended":false,"created_at":"2017-12-10T07:37:39+00:00","login_autocomplete":"jornari","login_exact":"jornari","name":"Jørn Ari","name_autocomplete":"Jørn Ari","orcid":null,"icon":"https://static.inaturalist.org/attachments/users/icons/730989/thumb.jpg?1548745022","observations_count":2273,"identifications_count":4720,"journal_posts_count":0,"activity_count":6993,"universal_search_rank":2273,"roles":[],"site_id":1,"icon_url":"https://static.inaturalist.org/attachments/users/icons/730989/medium.jpg?1548745022"}}],"identifiers":[{"user_id":730989,"count":3630,"user":{"id":730989,"login":"jornari","spam":false,"suspended":false,"created_at":"2017-12-10T07:37:39+00:00","login_autocomplete":"jornari","login_exact":"jornari","name":"Jørn Ari","name_autocomplete":"Jørn Ari","orcid":null,"icon":"https://static.inaturalist.org/attachments/users/icons/730989/thumb.jpg?1548745022","observations_count":2273,"identifications_count":4720,"journal_posts_count":0,"activity_count":6993,"universal_search_rank":2273,"roles":[],"site_id":1,"icon_url":"https://static.inaturalist.org/attachments/users/icons/730989/medium.jpg?1548745022"}},{"user_id":26473,"count":2146,"user":{"id":26473,"login":"jpsilva","spam":false,"suspended":false,"created_at":"2013-11-28T10:38:38+00:00","login_autocomplete":"jpsilva","login_exact":"jpsilva","name":"João Pedro Silva","name_autocomplete":"João Pedro Silva","orcid":null,"icon":"https://static.inaturalist.org/attachments/users/icons/26473/thumb.jpg?1475541089","observations_count":4418,"identifications_count":10055,"journal_posts_count":0,"activity_count":14473,"universal_search_rank":4418,"roles":["curator"],"site_id":1,"icon_url":"https://static.inaturalist.org/attachments/users/icons/26473/medium.jpg?1475541089"}},{"user_id":534826,"count":2031,"user":{"id":534826,"login":"jmgrinde","spam":false,"suspended":false,"created_at":"2017-07-16T14:19:15+00:00","login_autocomplete":"jmgrinde","login_exact":"jmgrinde","name":"","name_autocomplete":"","orcid":null,"icon":null,"observations_count":2296,"identifications_count":11956,"journal_posts_count":0,"activity_count":14252,"universal_search_rank":2296,"roles":[],"site_id":1,"icon_url":null}},{"user_id":614374,"count":1319,"user":{"id":614374,"login":"juhakinnunen","spam":false,"suspended":false,"created_at":"2017-09-03T19:28:24+00:00","login_autocomplete":"juhakinnunen","login_exact":"juhakinnunen","name":"Juha Kinnunen","name_autocomplete":"Juha Kinnunen","orcid":null,"icon":"https://static.inaturalist.org/attachments/users/icons/614374/thumb.gif?1542975190","observations_count":5278,"identifications_count":50611,"journal_posts_count":0,"activity_count":55889,"universal_search_rank":5278,"roles":["curator"],"site_id":1,"icon_url":"https://static.inaturalist.org/attachments/users/icons/614374/medium.gif?1542975190"}},{"user_id":29729,"count":1284,"user":{"id":29729,"login":"ldacosta","spam":false,"suspended":false,"created_at":"2014-02-02T19:12:57+00:00","login_autocomplete":"ldacosta","login_exact":"ldacosta","name":"Luis da Costa","name_autocomplete":"Luis da Costa","orcid":null,"icon":"https://static.inaturalist.org/attachments/users/icons/29729/thumb.jpeg?1475543064","observations_count":4640,"identifications_count":162702,"journal_posts_count":0,"activity_count":167342,"universal_search_rank":4640,"roles":["curator"],"site_id":1,"icon_url":"https://static.inaturalist.org/attachments/users/icons/29729/medium.jpeg?1475543064"}}]},{"rank":47,"place_id":7800,"place_name":"Poland","obs_count":22451,"observers":[{"user_id":742419,"observation_count":3401,"species_count":1063,"user":{"id":742419,"login":"grzegorzgrzejszczak","spam":false,"suspended":false,"created_at":"2018-01-02T11:38:31+00:00","login_autocomplete":"grzegorzgrzejszczak","login_exact":"grzegorzgrzejszczak","name":"Grzegorz Grzejszczak","name_autocomplete":"Grzegorz Grzejszczak","orcid":null,"icon":"https://static.inaturalist.org/attachments/users/icons/742419/thumb.jpg?1524385118","observations_count":4195,"identifications_count":3141,"journal_posts_count":0,"activity_count":7336,"universal_search_rank":4195,"roles":[],"site_id":1,"icon_url":"https://static.inaturalist.org/attachments/users/icons/742419/medium.jpg?1524385118"}},{"user_id":1257588,"observation_count":2145,"species_count":808,"user":{"id":1257588,"login":"wojtest","spam":false,"suspended":false,"created_at":"2018-10-05T12:18:57+00:00","login_autocomplete":"wojtest","login_exact":"wojtest","name":"","name_autocomplete":"","orcid":null,"icon":"https://static.inaturalist.org/attachments/users/icons/1257588/thumb.jpeg?1541390031","observations_count":3342,"identifications_count":8964,"journal_posts_count":0,"activity_count":12306,"universal_search_rank":3342,"roles":[],"site_id":1,"icon_url":"https://static.inaturalist.org/attachments/users/icons/1257588/medium.jpeg?1541390031"}},{"user_id":756146,"observation_count":1166,"species_count":300,"user":{"id":756146,"login":"slovianka","spam":false,"suspended":false,"created_at":"2018-01-30T21:56:14+00:00","login_autocomplete":"slovianka","login_exact":"slovianka","name":"Adrianna Rafalska","name_autocomplete":"Adrianna Rafalska","orcid":null,"icon":"https://static.inaturalist.org/attachments/users/icons/756146/thumb.jpg?1557402027","observations_count":1315,"identifications_count":105,"journal_posts_count":0,"activity_count":1420,"universal_search_rank":1315,"roles":[],"site_id":1,"icon_url":"https://static.inaturalist.org/attachments/users/icons/756146/medium.jpg?1557402027"}},{"user_id":18823,"observation_count":1096,"species_count":431,"user":{"id":18823,"login":"ahospers","spam":false,"suspended":false,"created_at":"2013-07-08T12:50:11+00:00","login_autocomplete":"ahospers","login_exact":"ahospers","name":"Andre Hospers","name_autocomplete":"Andre Hospers","orcid":null,"icon":"https://static.inaturalist.org/attachments/users/icons/18823/thumb.jpg?1534618158","observations_count":130138,"identifications_count":351,"journal_posts_count":33,"activity_count":130522,"universal_search_rank":130138,"roles":[],"site_id":1,"icon_url":"https://static.inaturalist.org/attachments/users/icons/18823/medium.jpg?1534618158"}},{"user_id":1311619,"observation_count":701,"species_count":483,"user":{"id":1311619,"login":"max09","spam":false,"suspended":false,"created_at":"2018-11-01T18:50:10+00:00","login_autocomplete":"max09","login_exact":"max09","name":"","name_autocomplete":"","orcid":null,"icon":null,"observations_count":899,"identifications_count":259,"journal_posts_count":0,"activity_count":1158,"universal_search_rank":899,"roles":[],"site_id":1,"icon_url":null}}],"identifiers":[{"user_id":1257588,"count":2444,"user":{"id":1257588,"login":"wojtest","spam":false,"suspended":false,"created_at":"2018-10-05T12:18:57+00:00","login_autocomplete":"wojtest","login_exact":"wojtest","name":"","name_autocomplete":"","orcid":null,"icon":"https://static.inaturalist.org/attachments/users/icons/1257588/thumb.jpeg?1541390031","observations_count":3342,"identifications_count":8964,"journal_posts_count":0,"activity_count":12306,"universal_search_rank":3342,"roles":[],"site_id":1,"icon_url":"https://static.inaturalist.org/attachments/users/icons/1257588/medium.jpeg?1541390031"}},{"user_id":281423,"count":1703,"user":{"id":281423,"login":"almantas","spam":false,"suspended":false,"created_at":"2016-08-03T15:59:33+00:00","login_autocomplete":"almantas","login_exact":"almantas","name":"Almantas Kulbis","name_autocomplete":"Almantas Kulbis","orcid":null,"icon":"https://static.inaturalist.org/attachments/users/icons/281423/thumb.jpg?1481051528","observations_count":4642,"identifications_count":15104,"journal_posts_count":0,"activity_count":19746,"universal_search_rank":4642,"roles":[],"site_id":1,"icon_url":"https://static.inaturalist.org/attachments/users/icons/281423/medium.jpg?1481051528"}},{"user_id":29729,"count":1031,"user":{"id":29729,"login":"ldacosta","spam":false,"suspended":false,"created_at":"2014-02-02T19:12:57+00:00","login_autocomplete":"ldacosta","login_exact":"ldacosta","name":"Luis da Costa","name_autocomplete":"Luis da Costa","orcid":null,"icon":"https://static.inaturalist.org/attachments/users/icons/29729/thumb.jpeg?1475543064","observations_count":4640,"identifications_count":162702,"journal_posts_count":0,"activity_count":167342,"universal_search_rank":4640,"roles":["curator"],"site_id":1,"icon_url":"https://static.inaturalist.org/attachments/users/icons/29729/medium.jpeg?1475543064"}},{"user_id":180811,"count":620,"user":{"id":180811,"login":"borisb","spam":false,"suspended":false,"created_at":"2016-02-18T10:19:19+00:00","login_autocomplete":"borisb","login_exact":"borisb","name":"","name_autocomplete":"","orcid":null,"icon":null,"observations_count":0,"identifications_count":156105,"journal_posts_count":0,"activity_count":156105,"universal_search_rank":0,"roles":["curator"],"site_id":1,"icon_url":null}},{"user_id":1005840,"count":576,"user":{"id":1005840,"login":"bobwardell","spam":false,"suspended":false,"created_at":"2018-06-04T10:30:32+00:00","login_autocomplete":"bobwardell","login_exact":"bobwardell","name":"R.H.Wardell","name_autocomplete":"R.H.Wardell","orcid":null,"icon":"https://static.inaturalist.org/attachments/users/icons/1005840/thumb.jpg?1533224723","observations_count":5720,"identifications_count":29923,"journal_posts_count":0,"activity_count":35643,"universal_search_rank":5720,"roles":[],"site_id":1,"icon_url":"https://static.inaturalist.org/attachments/users/icons/1005840/medium.jpg?1533224723"}}]},{"rank":48,"place_id":8266,"place_name":"Lithuania","obs_count":21509,"observers":[{"user_id":281423,"observation_count":3281,"species_count":1393,"user":{"id":281423,"login":"almantas","spam":false,"suspended":false,"created_at":"2016-08-03T15:59:33+00:00","login_autocomplete":"almantas","login_exact":"almantas","name":"Almantas Kulbis","name_autocomplete":"Almantas Kulbis","orcid":null,"icon":"https://static.inaturalist.org/attachments/users/icons/281423/thumb.jpg?1481051528","observations_count":4642,"identifications_count":15104,"journal_posts_count":0,"activity_count":19746,"universal_search_rank":4642,"roles":[],"site_id":1,"icon_url":"https://static.inaturalist.org/attachments/users/icons/281423/medium.jpg?1481051528"}},{"user_id":1369015,"observation_count":2999,"species_count":913,"user":{"id":1369015,"login":"jurga_li","spam":false,"suspended":false,"created_at":"2018-11-27T11:52:15+00:00","login_autocomplete":"jurga_li","login_exact":"jurga_li","name":"","name_autocomplete":"","orcid":null,"icon":"https://static.inaturalist.org/attachments/users/icons/1369015/thumb.jpg?1543668829","observations_count":4944,"identifications_count":10335,"journal_posts_count":0,"activity_count":15279,"universal_search_rank":4944,"roles":[],"site_id":1,"icon_url":"https://static.inaturalist.org/attachments/users/icons/1369015/medium.jpg?1543668829"}},{"user_id":1198134,"observation_count":1275,"species_count":324,"user":{"id":1198134,"login":"solokultas","spam":false,"suspended":false,"created_at":"2018-09-10T19:58:04+00:00","login_autocomplete":"solokultas","login_exact":"solokultas","name":"","name_autocomplete":"","orcid":null,"icon":"https://static.inaturalist.org/attachments/users/icons/1198134/thumb.jpg?1539363408","observations_count":1375,"identifications_count":1303,"journal_posts_count":0,"activity_count":2678,"universal_search_rank":1375,"roles":[],"site_id":1,"icon_url":"https://static.inaturalist.org/attachments/users/icons/1198134/medium.jpg?1539363408"}},{"user_id":737697,"observation_count":938,"species_count":548,"user":{"id":737697,"login":"tomasp","spam":false,"suspended":false,"created_at":"2017-12-19T09:09:22+00:00","login_autocomplete":"tomasp","login_exact":"tomasp","name":"Tomas P.","name_autocomplete":"Tomas P.","orcid":null,"icon":"https://static.inaturalist.org/attachments/users/icons/737697/thumb.jpeg?1513676468","observations_count":990,"identifications_count":671,"journal_posts_count":0,"activity_count":1661,"universal_search_rank":990,"roles":[],"site_id":1,"icon_url":"https://static.inaturalist.org/attachments/users/icons/737697/medium.jpeg?1513676468"}},{"user_id":726635,"observation_count":779,"species_count":426,"user":{"id":726635,"login":"ausrazilinskiene","spam":false,"suspended":false,"created_at":"2017-12-05T09:45:51+00:00","login_autocomplete":"ausrazilinskiene","login_exact":"ausrazilinskiene","name":"Ausra Zilinskiene","name_autocomplete":"Ausra Zilinskiene","orcid":null,"icon":"https://static.inaturalist.org/attachments/users/icons/726635/thumb.jpg?1512495351","observations_count":779,"identifications_count":30,"journal_posts_count":0,"activity_count":809,"universal_search_rank":779,"roles":[],"site_id":1,"icon_url":"https://static.inaturalist.org/attachments/users/icons/726635/medium.jpg?1512495351"}}],"identifiers":[{"user_id":281423,"count":5000,"user":{"id":281423,"login":"almantas","spam":false,"suspended":false,"created_at":"2016-08-03T15:59:33+00:00","login_autocomplete":"almantas","login_exact":"almantas","name":"Almantas Kulbis","name_autocomplete":"Almantas Kulbis","orcid":null,"icon":"https://static.inaturalist.org/attachments/users/icons/281423/thumb.jpg?1481051528","observations_count":4642,"identifications_count":15104,"journal_posts_count":0,"activity_count":19746,"universal_search_rank":4642,"roles":[],"site_id":1,"icon_url":"https://static.inaturalist.org/attachments/users/icons/281423/medium.jpg?1481051528"}},{"user_id":726089,"count":1675,"user":{"id":726089,"login":"laukines_pievos","spam":false,"suspended":false,"created_at":"2017-12-04T18:07:30+00:00","login_autocomplete":"laukines_pievos","login_exact":"laukines_pievos","name":"Laukinės Pievos","name_autocomplete":"Laukinės Pievos","orcid":null,"icon":"https://static.inaturalist.org/attachments/users/icons/726089/thumb.jpeg?1554662751","observations_count":437,"identifications_count":14177,"journal_posts_count":0,"activity_count":14614,"universal_search_rank":437,"roles":[],"site_id":1,"icon_url":"https://static.inaturalist.org/attachments/users/icons/726089/medium.jpeg?1554662751"}},{"user_id":1161364,"count":1447,"user":{"id":1161364,"login":"kastani","spam":false,"suspended":false,"created_at":"2018-08-25T09:46:05+00:00","login_autocomplete":"kastani","login_exact":"kastani","name":"ruslan","name_autocomplete":"ruslan","orcid":null,"icon":"https://static.inaturalist.org/attachments/users/icons/1161364/thumb.jpeg?1535784606","observations_count":766,"identifications_count":40412,"journal_posts_count":0,"activity_count":41178,"universal_search_rank":766,"roles":[],"site_id":1,"icon_url":"https://static.inaturalist.org/attachments/users/icons/1161364/medium.jpeg?1535784606"}},{"user_id":1183872,"count":1410,"user":{"id":1183872,"login":"leschij","spam":false,"suspended":false,"created_at":"2018-09-04T16:13:04+00:00","login_autocomplete":"leschij","login_exact":"leschij","name":"Станислав","name_autocomplete":"Станислав","orcid":null,"icon":"https://static.inaturalist.org/attachments/users/icons/1183872/thumb.jpg?1536078351","observations_count":1638,"identifications_count":1860,"journal_posts_count":0,"activity_count":3498,"universal_search_rank":1638,"roles":[],"site_id":1,"icon_url":"https://static.inaturalist.org/attachments/users/icons/1183872/medium.jpg?1536078351"}},{"user_id":29729,"count":1107,"user":{"id":29729,"login":"ldacosta","spam":false,"suspended":false,"created_at":"2014-02-02T19:12:57+00:00","login_autocomplete":"ldacosta","login_exact":"ldacosta","name":"Luis da Costa","name_autocomplete":"Luis da Costa","orcid":null,"icon":"https://static.inaturalist.org/attachments/users/icons/29729/thumb.jpeg?1475543064","observations_count":4640,"identifications_count":162702,"journal_posts_count":0,"activity_count":167342,"universal_search_rank":4640,"roles":["curator"],"site_id":1,"icon_url":"https://static.inaturalist.org/attachments/users/icons/29729/medium.jpeg?1475543064"}}]},{"rank":49,"place_id":8147,"place_name":"Luxembourg","obs_count":21096,"observers":[{"user_id":419580,"observation_count":2112,"species_count":496,"user":{"id":419580,"login":"paul_luap","spam":false,"suspended":false,"created_at":"2017-03-08T09:54:47+00:00","login_autocomplete":"paul_luap","login_exact":"paul_luap","name":"Paul Braun","name_autocomplete":"Paul Braun","orcid":"0000-0002-3620-6188","icon":"https://static.inaturalist.org/attachments/users/icons/419580/thumb.jpeg?1559478153","observations_count":2691,"identifications_count":2901,"journal_posts_count":1,"activity_count":5593,"universal_search_rank":2691,"roles":[],"site_id":1,"icon_url":"https://static.inaturalist.org/attachments/users/icons/419580/medium.jpeg?1559478153"}},{"user_id":942797,"observation_count":1380,"species_count":964,"user":{"id":942797,"login":"raedwulf68","spam":false,"suspended":false,"created_at":"2018-05-06T18:22:20+00:00","login_autocomplete":"raedwulf68","login_exact":"raedwulf68","name":"","name_autocomplete":"","orcid":null,"icon":"https://static.inaturalist.org/attachments/users/icons/942797/thumb.jpg?1525884176","observations_count":1557,"identifications_count":753,"journal_posts_count":0,"activity_count":2310,"universal_search_rank":1557,"roles":[],"site_id":1,"icon_url":"https://static.inaturalist.org/attachments/users/icons/942797/medium.jpg?1525884176"}},{"user_id":978746,"observation_count":608,"species_count":389,"user":{"id":978746,"login":"carlobraunert","spam":false,"suspended":false,"created_at":"2018-05-22T19:56:25+00:00","login_autocomplete":"carlobraunert","login_exact":"carlobraunert","name":"","name_autocomplete":"","orcid":null,"icon":"https://static.inaturalist.org/attachments/users/icons/978746/thumb.jpg?1554146145","observations_count":714,"identifications_count":860,"journal_posts_count":0,"activity_count":1574,"universal_search_rank":714,"roles":[],"site_id":1,"icon_url":"https://static.inaturalist.org/attachments/users/icons/978746/medium.jpg?1554146145"}},{"user_id":419170,"observation_count":521,"species_count":260,"user":{"id":419170,"login":"cecellina","spam":false,"suspended":false,"created_at":"2017-03-07T20:03:53+00:00","login_autocomplete":"cecellina","login_exact":"cecellina","name":"Ce Cellina","name_autocomplete":"Ce Cellina","orcid":null,"icon":"https://static.inaturalist.org/attachments/users/icons/419170/thumb.jpg?1516836232","observations_count":758,"identifications_count":676,"journal_posts_count":0,"activity_count":1434,"universal_search_rank":758,"roles":[],"site_id":1,"icon_url":"https://static.inaturalist.org/attachments/users/icons/419170/medium.jpg?1516836232"}},{"user_id":250740,"observation_count":520,"species_count":164,"user":{"id":250740,"login":"taniaw","spam":false,"suspended":false,"created_at":"2016-05-31T06:08:06+00:00","login_autocomplete":"taniaw","login_exact":"taniaw","name":"","name_autocomplete":"","orcid":null,"icon":null,"observations_count":642,"identifications_count":211,"journal_posts_count":0,"activity_count":853,"universal_search_rank":642,"roles":[],"site_id":1,"icon_url":null}}],"identifiers":[{"user_id":419580,"count":2627,"user":{"id":419580,"login":"paul_luap","spam":false,"suspended":false,"created_at":"2017-03-08T09:54:47+00:00","login_autocomplete":"paul_luap","login_exact":"paul_luap","name":"Paul Braun","name_autocomplete":"Paul Braun","orcid":"0000-0002-3620-6188","icon":"https://static.inaturalist.org/attachments/users/icons/419580/thumb.jpeg?1559478153","observations_count":2691,"identifications_count":2901,"journal_posts_count":1,"activity_count":5593,"universal_search_rank":2691,"roles":[],"site_id":1,"icon_url":"https://static.inaturalist.org/attachments/users/icons/419580/medium.jpeg?1559478153"}},{"user_id":86520,"count":1797,"user":{"id":86520,"login":"thierryh","spam":false,"suspended":false,"created_at":"2015-03-31T15:44:09+00:00","login_autocomplete":"thierryh","login_exact":"thierryh","name":"Thierry Helminger","name_autocomplete":"Thierry Helminger","orcid":null,"icon":"https://static.inaturalist.org/attachments/users/icons/86520/thumb.jpg?1555513719","observations_count":145,"identifications_count":1889,"journal_posts_count":0,"activity_count":2034,"universal_search_rank":145,"roles":[],"site_id":1,"icon_url":"https://static.inaturalist.org/attachments/users/icons/86520/medium.jpg?1555513719"}},{"user_id":76575,"count":1185,"user":{"id":76575,"login":"wollef","spam":false,"suspended":false,"created_at":"2015-02-14T10:14:30+00:00","login_autocomplete":"wollef","login_exact":"wollef","name":"Jean-Paul Wolff","name_autocomplete":"Jean-Paul Wolff","orcid":null,"icon":"https://static.inaturalist.org/attachments/users/icons/76575/thumb.jpeg?1535398116","observations_count":421,"identifications_count":1213,"journal_posts_count":0,"activity_count":1634,"universal_search_rank":421,"roles":[],"site_id":1,"icon_url":"https://static.inaturalist.org/attachments/users/icons/76575/medium.jpeg?1535398116"}},{"user_id":1019142,"count":1144,"user":{"id":1019142,"login":"svenjachristian","spam":false,"suspended":false,"created_at":"2018-06-11T07:24:42+00:00","login_autocomplete":"svenjachristian","login_exact":"svenjachristian","name":"Svenja Christian","name_autocomplete":"Svenja Christian","orcid":null,"icon":"https://static.inaturalist.org/attachments/users/icons/1019142/thumb.jpg?1533988608","observations_count":27,"identifications_count":1262,"journal_posts_count":0,"activity_count":1289,"universal_search_rank":27,"roles":[],"site_id":1,"icon_url":"https://static.inaturalist.org/attachments/users/icons/1019142/medium.jpg?1533988608"}},{"user_id":305,"count":1026,"user":{"id":305,"login":"vitalfranz","spam":false,"suspended":false,"created_at":"2009-11-13T12:15:18+00:00","login_autocomplete":"vitalfranz","login_exact":"vitalfranz","name":"Francesco Vitali","name_autocomplete":"Francesco Vitali","orcid":null,"icon":"https://static.inaturalist.org/attachments/users/icons/305/thumb.jpg?1524298733","observations_count":66,"identifications_count":24445,"journal_posts_count":0,"activity_count":24511,"universal_search_rank":66,"roles":["curator"],"site_id":1,"icon_url":"https://static.inaturalist.org/attachments/users/icons/305/medium.jpg?1524298733"}}]}]